grynn_pylib/__init__.py
grynn_pylib/decorators.py
grynn_pylib/utils.py
grynn_pylib/finance/options.py
grynn_pylib/finance/timeseries.py
grynn_pylib-0.3.1.dist-info/METADATA
grynn_pylib-0.3.1.dist-info/WHEEL
grynn_pylib-0.3.1.dist-info/licenses/LICENSE
grynn_pylib-0.3.1.dist-info/RECORD
