Metadata-Version: 2.4
Name: grynn_pylib
Version: 0.3.1
Summary: A Python library of general utility functions, by & for Grynn.
Author-email: Vishal Doshi <vishal.doshi@gmail.com>
License-Expression: MIT
License-File: LICENSE
Requires-Python: >=3.12
Requires-Dist: click>=8.1
Requires-Dist: exchange-calendars>=4.7
Requires-Dist: jinja2>=3.1.5
Requires-Dist: loguru>=0.7.2
Requires-Dist: matplotlib>=3.10.0
Requires-Dist: numpy>=2.1.2
Requires-Dist: pandas>=2.2
Requires-Dist: scipy>=1.14
Requires-Dist: tabulate>=0.9.0
Requires-Dist: toml>=0.10
Requires-Dist: xlsxwriter>=3.2.1
Requires-Dist: yfinance>=0.2.51
Provides-Extra: dev
Requires-Dist: ipykernel>=6.29.5; extra == 'dev'
Requires-Dist: ipympl>=0.9.6; extra == 'dev'
Requires-Dist: ipython>=8.31.0; extra == 'dev'
Requires-Dist: ipywidgets>=8.1.5; extra == 'dev'
Provides-Extra: test
Requires-Dist: pytest>=8.3.4; extra == 'test'
